Metadata-Version: 2.1
Name: pulumi-purrl
Version: 0.2.0
Summary: A Pulumi native provider for making API calls
Home-page: https://pulumi.com
License: Apache-2.0
Project-URL: Repository, https://github.com/pulumiverse/pulumi-purrl
Keywords: pulumi command category/utility kind/native
Platform: UNKNOWN
